inari/__init__.py
inari/__main__.py
inari/_internal/__init__.py
inari/_internal/_format.py
inari/_internal/_path.py
inari/_internal/_templates.py
inari/cli.py
inari/collectors.py
inari/mkdocs_plugin.py
inari/py.typed
inari-0.2.1.dist-info/entry_points.txt
inari-0.2.1.dist-info/LICENSE
inari-0.2.1.dist-info/WHEEL
inari-0.2.1.dist-info/METADATA
inari-0.2.1.dist-info/RECORD
