Metadata-Version: 2.1
Name: inari
Version: 0.2.1
Summary: Write docstrings in Markdown!
Home-page: https://tkamenoko.github.io/inari
License: MIT
Keywords: mkdocs,documentation,docstrings
Author: T.Kameyama
Author-email: tkamenoko@vivaldi.net
Requires-Python: >=3.9,<4.0
Classifier: Development Status :: 3 - Alpha
Classifier: Environment :: Console
Classifier: Environment :: Plugins
Classifier: Intended Audience :: Developers
Classifier: License :: OSI Approved :: MIT License
Classifier: Operating System :: OS Independent
Classifier: Programming Language :: Python :: 3
Classifier: Programming Language :: Python :: 3.9
Classifier: Topic :: Software Development :: Documentation
Provides-Extra: mkdocs
Requires-Dist: mkdocs (>=1.1.2,<2.0.0); extra == "mkdocs"
Project-URL: Documentation, https://tkamenoko.github.io/inari
Project-URL: Repository, https://github.com/tkamenoko/inari
